<xml><csb>
<dir>
<title>Monday</title>
<summary>Monday 8th April</summary>
<link>https://github.com/mattitch/images/raw/master/dtv/mon.xml</link>
<animated_thumbnail>https://github.com/mattitch/images/raw/master/Other/mon.gif</animated_thumbnail>
<fanart>https://github.com/mattitch/images/raw/master/Other/mon.jpg</fanart>
</dir>




<dir>
<title>Tuesday</title>
<summary>Tuesday 9th April</summary>
<link>https://github.com/mattitch/images/raw/master/dtv/tue.xml</link>
<animated_thumbnail>https://github.com/mattitch/images/raw/master/Other/tue.gif</animated_thumbnail>
<fanart>https://github.com/mattitch/images/raw/master/Other/tue.jpg</fanart>
</dir>





	
<dir>
<title>Wednesday</title>
<summary>Wedneday 10th April</summary>
<link>https://github.com/mattitch/images/raw/master/dtv/wed.xml</link>
<animated_thumbnail>https://github.com/mattitch/images/raw/master/Other/wed.gif</animated_thumbnail>
<fanart>https://github.com/mattitch/images/raw/master/Other/wed.jpg</fanart>
</dir>

	
<dir>
<title>Thursday</title>
<summary>Thursday 11th April</summary>
<link>https://github.com/mattitch/images/raw/master/dtv/thu.xml</link>
<animated_thumbnail>https://github.com/mattitch/images/raw/master/Other/thu.gif</animated_thumbnail>
<fanart>https://github.com/mattitch/images/raw/master/Other/thu.jpg</fanart>
</dir>





<dir>
<title>Friday</title>
<summary>Friday 12th April</summary>
<link>https://github.com/mattitch/images/raw/master/dtv/fri.xml</link>
<animated_thumbnail>https://github.com/mattitch/images/raw/master/Other/fri.gif</animated_thumbnail>
<fanart>https://github.com/mattitch/images/raw/master/Other/fri.jpg</fanart>
</dir>

<item>
	<title>[COLOR=gold]Salary[/COLOR]</title>
	<meta>
	<imdb>tt4477976</imdb>
	<content>episode</content>
	<tvshowtitle>Superstore</tvshowtitle>
	<year>2019</year>
	<season>4</season>
	<episode>15</episode>
	</meta>
	<link>
	<sublink>https://rapidgator.net/file/d33338279bf3a95c26866e3f1292e290/Superstore.S04E15.720p.WEB.H264-METCON.mkv.html</sublink>
	</link>
	<thumbnail>https://image.tmdb.org/t/p/w1280/aNqCjp1nlg5OPpYu7gX4GnIO7zU.jpg</thumbnail>
</item>

<item>
	<title>[COLOR=gold]Casecation[/COLOR]</title>
	<meta>
	<imdb>tt2467372</imdb>
	<content>episode</content>
	<tvshowtitle>Brooklyn Nine Nine</tvshowtitle>
	<year>2019</year>
	<season>6</season>
	<episode>12</episode>
	</meta>
	<link>
	<sublink>https://rapidgator.net/file/c88697380a646a0fbbc56328ff689bf1/Brooklyn.Nine-Nine.S06E12.720p.HDTV.x264-KILLERS.mkv</sublink>
	</link>
	<thumbnail>https://image.tmdb.org/t/p/w1280/imcxmIEU00wm8n1V4xL8mJYYH5Q.jpg</thumbnail>
</item>

<item>
	<title>[COLOR=gold]Sanctuary[/COLOR]</title>
	<meta>
	<imdb>tt5691552</imdb>
	<content>episode</content>
	<tvshowtitle>The Orville</tvshowtitle>
	<year>2019</year>
	<season>2</season>
	<episode>12</episode>
	</meta>
	<link>
	<sublink>https://rapidgator.net/file/52457d7fa96163087637660837e4bc11/the.orville.s02e12.1080p.web.x264-tbs.mkv.html</sublink>
	</link>
	<thumbnail>https://image.tmdb.org/t/p/w1280/8gB4zeP5OEU5r2dnXw9P87qJ1Di.jpg</thumbnail>
</item>

<item>
	<title>[COLOR=gold]A New Hope[/COLOR]</title>
	<meta>
	<imdb>tt8026448</imdb>
	<content>episode</content>
	<tvshowtitle>Tacoma FD</tvshowtitle>
	<year>2019</year>
	<season>1</season>
	<episode>3</episode>
	</meta>
	<link>
	<sublink>https://rapidgator.net/file/fc3820a1911b539870e62dc7763f859c/tacoma.fd.s01e03.uncensored.repack.720p.webrip.x264-tbs.mkv.html</sublink>
	</link>
	<thumbnail>https://image.tmdb.org/t/p/w1280/gQQ00nI9WWgdRlq7RLcBZWXKzS4.jpg</thumbnail>
</item>

<dir>
<title>Saturday[COLOR=red]>>>>>>[/COLOR]</title>
<summary>Saturday 13th April>>>>>>LATEST>>>>>></summary>
<link>https://github.com/mattitch/images/raw/master/dtv/sat.xml</link>
<animated_thumbnail>https://github.com/mattitch/images/raw/master/Latest/sat.gif</animated_thumbnail>
<fanart>https://github.com/mattitch/images/raw/master/Other/sat.jpg</fanart>
</dir>






<dir>
<title>Sunday</title>
<summary>Sunday 7th April</summary>
<link>https://github.com/mattitch/images/raw/master/dtv/sun.xml</link>
<animated_thumbnail>https://github.com/mattitch/images/raw/master/Other/sun.gif</animated_thumbnail>
<fanart>https://github.com/mattitch/images/raw/master/Other/sun.jpg</fanart>
</dir>

<dir>
<title>My Episodes To Watch</title>
<summary>Random New Episodes</summary>
<link>https://github.com/mattitch/images/raw/master/dtv/seps.xml</link>
</dir>


</csb></xml>